setup.py
binomgau_distribution/Binomialdistribution.py
binomgau_distribution/Gaussiandistribution.py
binomgau_distribution/Generaldistribution.py
binomgau_distribution/__init__.py
binomgau_distribution.egg-info/PKG-INFO
binomgau_distribution.egg-info/SOURCES.txt
binomgau_distribution.egg-info/dependency_links.txt
binomgau_distribution.egg-info/not-zip-safe
binomgau_distribution.egg-info/top_level.txt