Metadata-Version: 1.0
Name: binomgau-distribution
Version: 0.1
Summary: Gaussian and binomial distributions
Home-page: UNKNOWN
Author: Hillary Okello
Author-email: UNKNOWN
License: UNKNOWN
Platform: UNKNOWN
